{
  "subjects": [
    {
      "subjectName": "পদার্থবিজ্ঞান",
      "units": [
        {
          "unitName": "চিরায়ত পদার্থবিজ্ঞান (Classical Physics)",
          "parts": [
            {"partName": "শাস্ত্রীয় পদার্থবিজ্ঞান", "partDetails": "পদার্থ বিজ্ঞানের বিভিন্ন সূত্রের সমন্বয় যা আধুনিক, স্বয়ংসম্পূর্ণ এবং ব্যাপকভাবে প্রচলিত সূত্রগুলোর পূর্বনির্দেশ করে।"}
          ]
        },
        {
          "unitName": "আধুনিক পদার্থবিজ্ঞান (Modern Physics)",
          "parts": [
            {"partName": "কোয়ান্টাম পদার্থবিজ্ঞান ও আপেক্ষিকতত্ত্ব", "partDetails": "কোয়ান্টাম পদার্থবিজ্ঞান ও আপেক্ষিকতত্ত্ব কে কেন্দ্র করে যে পদার্থবিজ্ঞান গড়ে উঠেছে তাকে আধুনিক পদার্থবিজ্ঞান বলে।"}
          ]
        }
      ]
    }
  ]
}
